Metadata-Version: 1.1
Name: send-msg-slack
Version: 1.0.0
Summary: function generic for sent message to Slack
Home-page: https://github.com/pypa/sampleproject
Author: Alejandro Matallana
Author-email: alejandro.matallana@escala24x7.com
License: NOTFOUND
Keywords: slack,send,message,msg
Platform: UNKNOWN
Classifier: Development Status :: 4 - Beta
Classifier: Intended Audience :: Developers
Classifier: Topic :: Software Development :: Build Tools
Classifier: Programming Language :: Python :: 2.7
Classifier: Programming Language :: Python :: 3.4
Classifier: Programming Language :: Python :: 3.5
Classifier: Programming Language :: Python :: 3.6
Classifier: Programming Language :: Python :: 3.7
